wabdd/__init__.py
wabdd/__main__.py
wabdd/constants.py
wabdd/gpsoauth_helper.py
wabdd/utils.py
wabdd/wabackup.py
wabdd/commands/decrypt.py
wabdd/commands/download.py
wabdd/commands/token.py
wabdd-0.1.7.dist-info/METADATA
wabdd-0.1.7.dist-info/WHEEL
wabdd-0.1.7.dist-info/entry_points.txt
wabdd-0.1.7.dist-info/licenses/LICENSE
wabdd-0.1.7.dist-info/RECORD
