Metadata-Version: 2.4
Name: wabdd
Version: 0.1.7
Summary: WhatsApp Backup Google Drive Downloader Decryptor
Project-URL: source, https://github.com/giacomoferretti/whatsapp-backup-downloader-decryptor
Project-URL: issues, https://github.com/giacomoferretti/whatsapp-backup-downloader-decryptor/issues
Author-email: Giacomo Ferretti <giacomo.ferretti.00@gmail.com>
License-Expression: Apache-2.0
License-File: LICENSE
Requires-Python: <4,>=3.9
Requires-Dist: click>=8.1.8
Requires-Dist: gpsoauth>=2.0.0
Requires-Dist: inquirer>=3.4.0
Requires-Dist: pycryptodomex>=3.23.0
Requires-Dist: requests>=2.32.4
Requires-Dist: rich>=14.0.0
Requires-Dist: wa-crypt-tools>=0.1.0
